pylode/__init__.py
pylode/__main__.py
pylode/cli.py
pylode/profiles/__init__.py
pylode/profiles/ontpub.py
pylode/profiles/supermodel/__init__.py
pylode/profiles/supermodel/component/__init__.py
pylode/profiles/supermodel/component/example.py
pylode/profiles/supermodel/component/heading.py
pylode/profiles/supermodel/component/link.py
pylode/profiles/supermodel/component/preamble.py
pylode/profiles/supermodel/component/properties_table.py
pylode/profiles/supermodel/component/tooltip.py
pylode/profiles/supermodel/dataset.py
pylode/profiles/supermodel/fragment.py
pylode/profiles/supermodel/html.py
pylode/profiles/supermodel/loader.py
pylode/profiles/supermodel/model.py
pylode/profiles/supermodel/namespace.py
pylode/profiles/supermodel/query/__init__.py
pylode/profiles/supermodel/query/common.py
pylode/profiles/supermodel/query/property_shape.py
pylode/profiles/supermodel/random.py
pylode/profiles/supermodel/state.py
pylode/profiles/vocpub.py
pylode/pylode.css
pylode/rdf/dcterms-mod.ttl
pylode/rdf/licenses.ttl
pylode/rdf/ontdoc.ttl
pylode/rdf/owl.ttl
pylode/rdf/prov.ttl
pylode/rdf/rdf.ttl
pylode/rdf/rdfs-mod.ttl
pylode/rdf/sdo-mod.ttl
pylode/rdf/skos.ttl
pylode/rdf/void.ttl
pylode/rdf_elements.py
pylode/static/asciidoc.css
pylode/static/hierarchy.css
pylode/static/hierarchy.js
pylode/static/property-table-row.js
pylode/static/pylode.css
pylode/utils.py
pylode/version.py
pylode-3.2.1.dist-info/LICENSE
pylode-3.2.1.dist-info/METADATA
pylode-3.2.1.dist-info/WHEEL
pylode-3.2.1.dist-info/entry_points.txt
pylode-3.2.1.dist-info/RECORD
