Metadata-Version: 2.3
Name: pylode
Version: 3.2.1
Summary: An OWL ontology documentation tool using Python, based on LODE.
Author: Nicholas Car
Author-email: nick@kurrawong.net
Requires-Python: >=3.9,<4.0
Classifier: Programming Language :: Python :: 3
Classifier: Programming Language :: Python :: 3.9
Classifier: Programming Language :: Python :: 3.10
Classifier: Programming Language :: Python :: 3.11
Classifier: Programming Language :: Python :: 3.12
Classifier: Programming Language :: Python :: 3.13
Requires-Dist: Markdown (>=3.3.7,<4.0.0)
Requires-Dist: dominate (>=2.6.0,<3.0.0)
Requires-Dist: html5lib (>=1.1,<2.0)
Requires-Dist: httpx (>=0.25.0,<1.0.0)
Requires-Dist: rdflib (>=7.0.0,<8.0.0)
